setup.cfg
setup.py
bankers/__init__.py
bankers/deadlock.py
bankers.egg-info/PKG-INFO
bankers.egg-info/SOURCES.txt
bankers.egg-info/dependency_links.txt
bankers.egg-info/pbr.json
bankers.egg-info/top_level.txt