Metadata-Version: 1.1
Name: bankers
Version: 0.0.1
Summary: Bankers - This is an implementation of the banker's deadlock algorithm
Home-page: https://github.com/mkli90/Bankers
Author: Max Klingmann <KlingmannM@gmail.com>
Author-email: KlingmannM@gmail.com
License: GPLv3
Platform: UNKNOWN
Classifier: Intended Audience :: Developers
Classifier: License :: OSI Approved :: GNU General Public License v3 (GPLv3)
Classifier: Natural Language :: English
Classifier: Programming Language :: Python :: 3.4
Classifier: Topic :: Software Development :: Libraries
